azure/monitor/querymetrics/__init__.py
azure/monitor/querymetrics/_client.py
azure/monitor/querymetrics/_configuration.py
azure/monitor/querymetrics/_enums.py
azure/monitor/querymetrics/_helpers.py
azure/monitor/querymetrics/_models.py
azure/monitor/querymetrics/_patch.py
azure/monitor/querymetrics/_sdk_moniker.py
azure/monitor/querymetrics/_version.py
azure/monitor/querymetrics/py.typed
azure/monitor/querymetrics/_operations/__init__.py
azure/monitor/querymetrics/_operations/_operations.py
azure/monitor/querymetrics/_operations/_patch.py
azure/monitor/querymetrics/_utils/__init__.py
azure/monitor/querymetrics/_utils/model_base.py
azure/monitor/querymetrics/_utils/serialization.py
azure/monitor/querymetrics/_utils/utils.py
azure/monitor/querymetrics/aio/__init__.py
azure/monitor/querymetrics/aio/_client.py
azure/monitor/querymetrics/aio/_configuration.py
azure/monitor/querymetrics/aio/_patch.py
azure/monitor/querymetrics/aio/_operations/__init__.py
azure/monitor/querymetrics/aio/_operations/_operations.py
azure/monitor/querymetrics/aio/_operations/_patch.py
azure/monitor/querymetrics/models/__init__.py
azure/monitor/querymetrics/models/_enums.py
azure/monitor/querymetrics/models/_models.py
azure/monitor/querymetrics/models/_patch.py
azure_monitor_querymetrics-1.0.0.dist-info/LICENSE
azure_monitor_querymetrics-1.0.0.dist-info/METADATA
azure_monitor_querymetrics-1.0.0.dist-info/WHEEL
azure_monitor_querymetrics-1.0.0.dist-info/top_level.txt
azure_monitor_querymetrics-1.0.0.dist-info/RECORD
